geoacumen/__init__.py
geoacumen/db/.gitkeep
geoacumen/db/Geoacumen-Country.mmdb
python_geoacumen-2024.6.23.dist-info/LICENSE
python_geoacumen-2024.6.23.dist-info/METADATA
python_geoacumen-2024.6.23.dist-info/WHEEL
python_geoacumen-2024.6.23.dist-info/top_level.txt
python_geoacumen-2024.6.23.dist-info/RECORD
