Metadata-Version: 2.1
Name: python-geoacumen
Version: 2024.6.23
Summary: Library to access/distribute Geoacumen IP databases
Home-page: UNKNOWN
Author: Kevin Chung
Author-email: kchung@nyu.edu
License: Apache 2.0
Platform: UNKNOWN
Requires-Dist: maxminddb ==1.5.4
